matrix/__init__.py
matrix/zion/__init__.py
matrix/zion/zion.py
matrix_zion-0.1.0.dist-info/METADATA
matrix_zion-0.1.0.dist-info/WHEEL
matrix_zion-0.1.0.dist-info/entry_points.txt
matrix_zion-0.1.0.dist-info/RECORD
