Metadata-Version: 2.3
Name: matrix-zion
Version: 0.1.0
Summary: Framework para microserviços Python com arquitetura de plugins
License: MIT
Keywords: microservices,framework,python,plugins,architecture
Author: Tuyoshi Vinicius
Author-email: tuyoshi.vinicius@gmail.com
Requires-Python: >=3.10
Classifier: Development Status :: 3 - Alpha
Classifier: Intended Audience :: Developers
Classifier: License :: OSI Approved :: MIT License
Classifier: Programming Language :: Python :: 3
Classifier: Programming Language :: Python :: 3.10
Classifier: Programming Language :: Python :: 3.11
Classifier: Programming Language :: Python :: 3.12
Classifier: Topic :: Software Development :: Libraries :: Python Modules
Classifier: Topic :: Software Development :: Libraries :: Application Frameworks
Provides-Extra: all
Provides-Extra: aws
Provides-Extra: dev
Provides-Extra: fastapi
Requires-Dist: importlib-metadata (>=5.0.0) ; python_version < "3.10"
Requires-Dist: matrix-zion-aws (>=0.1.0) ; extra == "all"
Requires-Dist: matrix-zion-aws (>=0.1.0) ; extra == "aws"
Requires-Dist: matrix-zion-fastapi (>=0.1.0) ; extra == "all"
Requires-Dist: matrix-zion-fastapi (>=0.1.0) ; extra == "fastapi"
Requires-Dist: mypy (>=1.17.0) ; extra == "dev"
Requires-Dist: pytest (>=8.0.0) ; extra == "dev"
Requires-Dist: pytest-cov (>=4.0.0) ; extra == "dev"
Requires-Dist: python-dotenv (>=1.0.0)
Requires-Dist: ruff (>=0.8.0) ; extra == "dev"
Project-URL: Bug Reports, https://github.com/tuyoshivinicius/python-microservice-v2/issues
Project-URL: Documentation, https://github.com/tuyoshivinicius/python-microservice-v2/blob/main/README.md
Project-URL: Homepage, https://github.com/tuyoshivinicius/python-microservice-v2
Project-URL: Repository, https://github.com/tuyoshivinicius/python-microservice-v2
